{"General Items":["Ghost Orb of the Planeswalker","Empowering Elements","Spirit Crusher","Flail of the Iron Will","Flail of the Death Charge"],"belt":["Heavy Belt of the World Runner","Battleseeker Belt","Belt of Fury","Strap of the Iron Will","Belt of the Death Charge"],"arms":["Heavy Gauntlets of the World Runner","Battleseeker Arms","Bracers of Fury","Cuffs of the Iron Will","Bracers of the Death Charge"],"head":["Heavy Helm of the World Runner","Battleseeker Helmet","Mask of Fury","Horns of the Iron Will","Horns of the Death Charge"],"shoulder":["Heavy Pauldrons of the World Runner","Battleseeker Shoulders","Pauldrons of Fury","Mantle of the Iron Will","Shoulders of the Death Charge"],"tail":["Tail of Fury","Tail of the Iron Will","Tail of the Death Charge"],"set":["Heavy Armor of the World Runner","Battleseeker","Barathrum's Fury","Vestments of the Iron Will","Death Charge"]}