[{"name":"(arms) Radiant Crystal Bracer","key":"Radiant Crystal Bracer"},{"name":"(head) Radiant Crystal Crown","key":"Radiant Crystal Crown"},{"name":"(shoulder) Radiant Crystal Pauldrons","key":"Radiant Crystal Pauldrons"},{"name":"(back) Radiant Crystal Crests","key":"Radiant Crystal Crests"},{"name":"(shoulder) Shoulders of the Comet's Tail","key":"Shoulders of the Comet's Tail"},{"name":"(head) Crown of the Comet's Tail","key":"Crown of the Comet's Tail"},{"name":"(back) Direstone Crests","key":"Direstone Crests"},{"name":"(arms) Direstone Bracers","key":"Direstone Bracers"},{"name":"(head) Direstone Crown","key":"Direstone Crown"},{"name":"(shoulder) Direstone Pauldrons","key":"Direstone Pauldrons"},{"name":"(back) Crests of Polymorphia","key":"Crests of Polymorphia"},{"name":"(head) Crown of Polymorphia","key":"Crown of Polymorphia"},{"name":"(shoulder) Pauldrons of Polymorphia","key":"Pauldrons of Polymorphia"},{"name":"(arms) Bracers of Polymorphia","key":"Bracers of Polymorphia"},{"name":"(head) Frost Shard Crown","key":"Frost Shard Crown"},{"name":"(shoulder) Frost Shard Pauldrons","key":"Frost Shard Pauldrons"},{"name":"(arms) Frost Shard Armlets","key":"Frost Shard Armlets"},{"name":"(arms) Birot's Bracers of Dignity","key":"Birot's Bracers of Dignity"},{"name":"(shoulder) Birot's Crests of Dignity","key":"Birot's Crests of Dignity"},{"name":"(head) Birot's Helm of Dignity","key":"Birot's Helm of Dignity"},{"name":"(head) Crown of the Falling Comet","key":"Crown of the Falling Comet"},{"name":"(shoulder) Crests of the Falling Comet","key":"Crests of the Falling Comet"},{"name":"(arms) Armlets of the Falling Comet","key":"Armlets of the Falling Comet"},{"name":"(arms) Thrashers of the Dreadful Abyss","key":"Thrashers of the Dreadful Abyss"},{"name":"(head) Tendrils of the Dreadful Abyss","key":"Tendrils of the Dreadful Abyss"},{"name":"(back) Spines of the Dreadful Abyss","key":"Spines of the Dreadful Abyss"},{"name":"(arms) Gift of the Sea Arms","key":"Gift of the Sea Arms"},{"name":"(misc) Gift of the Sea Fin","key":"Gift of the Sea Fin"},{"name":"(head) Gift of the Sea Head","key":"Gift of the Sea Head"},{"name":"(shoulder) Gift of the Sea Shoulders","key":"Gift of the Sea Shoulders"},{"name":"(back) Gift of the Sea Dorsal Wings","key":"Gift of the Sea Dorsal Wings"},{"name":"(arms) Ancient Armor Arms","key":"Ancient Armor Arms"},{"name":"(back) Ancient Armor Back","key":"Ancient Armor Back"},{"name":"(misc) Ancient Armor Breastplates","key":"Ancient Armor Breastplates"},{"name":"(head) Ancient Armor Helmet","key":"Ancient Armor Helmet"},{"name":"(shoulder) Ancient Armor Shoulder Shields","key":"Ancient Armor Shoulder Shields"},{"name":"Treasure of Tidal Power","key":"Treasure of Tidal Power"},{"name":"(set) Direstone Bindings","key":"Direstone Bindings"},{"name":"(set) Radiant Crystal Bindings","key":"Radiant Crystal Bindings"},{"name":"(set) Shards of Polymorphia","key":"Shards of Polymorphia"},{"name":"(set) Bindings of Frost","key":"Bindings of Frost"},{"name":"(set) Birot's Bindings","key":"Birot's Bindings"},{"name":"(set) Shards of the Falling Comet","key":"Shards of the Falling Comet"},{"name":"(set) Luminary of the Dreadful Abyss","key":"Luminary of the Dreadful Abyss"},{"name":"(set) Gift of the Sea","key":"Gift of the Sea"},{"name":"(set) Ancient Armor","key":"Ancient Armor"}]